{"type":"FeatureCollection","features":[{"type":"Feature","properties":{"category":"Mixed","short_description_en":"Situated near the southern margin of the Red River Delta, the Trang An Landscape Complex is a spectacular landscape of limestone karst peaks permeated with valleys, many of them partly submerged and surrounded by steep, almost vertical cliffs.","name_fr":"Complexe paysager de Trang An","continent_en":"Asia and the Pacific","justification_fr":null,"country_en":"Viet Nam","longitude":105.896388889,"justification_en":null,"latitude":20.2566666667,"date_inscribed":"2014/01/01","continent_fr":"Asie et pacifique","area_hectares":6172,"short_description_fr":"Situé sur la rive méridionale du  delta du fleuve Rouge, Trang An est un spectaculaire paysage de pitons karstiques sillonné de vallées, pour certaines immergées, et encadré de falaises abruptes, presque verticales. L’exploration de quelques-unes des grottes les plus en altitude qui ponctuent ce paysage a mis au jour des traces archéologiques d’une activité humaine qui remonte à 30 000 ans environ. Elles illustrent l’occupation de ce massif par des chasseurs-cueilleurs et leur adaptation aux changements climatiques et environnementaux. Le bien comprend aussi Hoa Lu, l’ancienne capitale du Viet Nam aux Xe et XIe siècles, ainsi que des temples, des pagodes et des paysages de rizières, de villages et de lieux sacrés.","name_en":"Trang An Landscape Complex","geographical_coordinates":"(2:20.2566666667,105.896388889)","country_fr":"Viet Nam","danger_list":null,"img":"https://whc.unesco.org/uploads/thumbs/site_1438_0008-360-360-20140623145733.jpg"},"geometry":{"type":"Point","coordinates":[105.896388889,20.2566666667]}}]}